home_secret/__init__.py
home_secret/_version.py
home_secret/api.py
home_secret/docs/__init__.py
home_secret/home_secret.json
home_secret/home_secret.py
home_secret/paths.py
home_secret/tests/__init__.py
home_secret/tests/helper.py
home_secret/vendor/__init__.py
home_secret/vendor/pytest_cov_helper.py
home_secret-0.1.3.dist-info/AUTHORS.rst
home_secret-0.1.3.dist-info/LICENSE.txt
home_secret-0.1.3.dist-info/METADATA
home_secret-0.1.3.dist-info/WHEEL
home_secret-0.1.3.dist-info/RECORD
